pso_logger/__init__.py
pso_logger/pso_logging.py
pso_logger/test_py.py
pso_logger-1.0.1.dist-info/METADATA
pso_logger-1.0.1.dist-info/WHEEL
pso_logger-1.0.1.dist-info/RECORD
